color_df-0.1.0.dist-info/licenses/LICENSE
color_df_module/color_df.py
color_df_module/init.py
color_df-0.1.0.dist-info/METADATA
color_df-0.1.0.dist-info/WHEEL
color_df-0.1.0.dist-info/top_level.txt
color_df-0.1.0.dist-info/RECORD
